lu/__init__.py
lu/__main__.py
lu/core.py
lu/lu.py
lu-0.1.3.dev0.dist-info/DESCRIPTION.rst
lu-0.1.3.dev0.dist-info/METADATA
lu-0.1.3.dev0.dist-info/RECORD
lu-0.1.3.dev0.dist-info/WHEEL
lu-0.1.3.dev0.dist-info/entry_points.txt
lu-0.1.3.dev0.dist-info/metadata.json
lu-0.1.3.dev0.dist-info/top_level.txt
