Metadata-Version: 2.0
Name: lu
Version: 0.1.3.dev0
Summary: lu - a CLI dictionary tool
Home-page: https://github.com/TaipaXu/lu
Author: taipa
Author-email: taipa@qq.com
License: GPL v3.0
Keywords: dictionary dict word lookup terminal
Platform: UNKNOWN
Requires-Dist: requests
